httpcase/__init__.py
httpcase/httpcase.py
httpcase-1.0.17.dist-info/METADATA
httpcase-1.0.17.dist-info/WHEEL
httpcase-1.0.17.dist-info/entry_points.txt
httpcase-1.0.17.dist-info/top_level.txt
httpcase-1.0.17.dist-info/RECORD
