Metadata-Version: 2.1
Name: httpcase
Version: 1.0.17
Summary: HttpCase - api auto test tool.
Home-page: https://github.com/roseboy/httpcase
Author: Mr.K
Author-email: roseboy@live.com
License: UNKNOWN
Platform: UNKNOWN
Requires-Dist: requests (>=2.19.1)
Requires-Dist: tqdm (>=4.61.1)
